redis_stream_logger.abi3.so
redis_stream_logger-0.1.2.dist-info/METADATA
redis_stream_logger-0.1.2.dist-info/WHEEL
redis_stream_logger-0.1.2.dist-info/top_level.txt
redis_stream_logger-0.1.2.dist-info/RECORD
redis_stream_logger-0.1.2.dist-info/licenses/LICENSE
