Metadata-Version: 2.4
Name: redis-stream-logger
Version: 0.1.2
Summary: High-performance Redis Stream logging handler with Cython compilation
Home-page: https://github.com/techmaju/logging
Author: TechMaju
Author-email: TechMaju <development@techmaju.com>
License: MIT
Project-URL: Homepage, https://github.com/techmaju/logging
Keywords: redis,logging,stream,cython,performance
Classifier: Development Status :: 4 - Beta
Classifier: Intended Audience :: Developers
Classifier: Programming Language :: Python :: 3
Classifier: Programming Language :: Python :: 3.7
Classifier: Programming Language :: Python :: 3.8
Classifier: Programming Language :: Python :: 3.9
Classifier: Programming Language :: Python :: 3.10
Classifier: Programming Language :: Python :: 3.11
Classifier: Programming Language :: Python :: 3.12
Classifier: Programming Language :: Cython
Requires-Python: >=3.7
License-File: LICENSE
Requires-Dist: redis>=4.0.0
Provides-Extra: dev
Requires-Dist: cython>=0.29; extra == "dev"
Requires-Dist: wheel; extra == "dev"
Requires-Dist: build; extra == "dev"
Dynamic: author
Dynamic: home-page
Dynamic: license-file
Dynamic: requires-python
